vocabslim/__init__.py
vocabslim/cli.py
vocabslim/core.py
vocabslim-0.1.4.dist-info/licenses/LICENSE
vocabslim-0.1.4.dist-info/METADATA
vocabslim-0.1.4.dist-info/WHEEL
vocabslim-0.1.4.dist-info/entry_points.txt
vocabslim-0.1.4.dist-info/top_level.txt
vocabslim-0.1.4.dist-info/RECORD
