Metadata-Version: 2.4
Name: vocabslim
Version: 0.1.4
Summary: A package to reduce the size of Hugging Face models via Vocabulary Slimming
Author-email: Andy1314Chen <chenzq@mail.ustc.edu.cn>
License:                                  Apache License
Project-URL: Homepage, https://github.com/Andy1314Chen/vocab-slim
Project-URL: Repository, https://github.com/Andy1314Chen/vocab-slim.git
Classifier: Development Status :: 3 - Alpha
Classifier: Intended Audience :: Science/Research
Classifier: License :: OSI Approved :: Apache Software License
Classifier: Programming Language :: Python :: 3
Classifier: Topic :: Scientific/Engineering :: Artificial Intelligence
Requires-Python: >=3.7
License-File: LICENSE
Requires-Dist: torch>=2.0.0
Requires-Dist: transformers>=4.30.0
Requires-Dist: datasets>=2.12.0
Requires-Dist: numpy>=1.24.0
Requires-Dist: tqdm>=4.65.0
Dynamic: license-file
